ShiyongJisuanjiShijueShizhanXiangmuJingtongOpencvChuyi/README.md
ShiyongJisuanjiShijueShizhanXiangmuJingtongOpencvChuyi/__init__.py
ShiyongJisuanjiShijueShizhanXiangmuJingtongOpencvChuyi/__main__.py
ShiyongJisuanjiShijueShizhanXiangmuJingtongOpencvChuyi/file.epub
ShiyongJisuanjiShijueShizhanXiangmuJingtongOpencvChuyi/index.html
ShiyongJisuanjiShijueShizhanXiangmuJingtongOpencvChuyi/css/__init__.py
ShiyongJisuanjiShijueShizhanXiangmuJingtongOpencvChuyi/css/annotations.css
ShiyongJisuanjiShijueShizhanXiangmuJingtongOpencvChuyi/css/main.css
ShiyongJisuanjiShijueShizhanXiangmuJingtongOpencvChuyi/css/normalize.css
ShiyongJisuanjiShijueShizhanXiangmuJingtongOpencvChuyi/css/popup.css
ShiyongJisuanjiShijueShizhanXiangmuJingtongOpencvChuyi/font/__init__.py
ShiyongJisuanjiShijueShizhanXiangmuJingtongOpencvChuyi/font/fontello.eot
ShiyongJisuanjiShijueShizhanXiangmuJingtongOpencvChuyi/font/fontello.svg
ShiyongJisuanjiShijueShizhanXiangmuJingtongOpencvChuyi/font/fontello.ttf
ShiyongJisuanjiShijueShizhanXiangmuJingtongOpencvChuyi/font/fontello.woff
ShiyongJisuanjiShijueShizhanXiangmuJingtongOpencvChuyi/img/__init__.py
ShiyongJisuanjiShijueShizhanXiangmuJingtongOpencvChuyi/img/annotator-glyph-sprite.png
ShiyongJisuanjiShijueShizhanXiangmuJingtongOpencvChuyi/img/annotator-icon-sprite.png
ShiyongJisuanjiShijueShizhanXiangmuJingtongOpencvChuyi/img/apple-touch-icon.png
ShiyongJisuanjiShijueShizhanXiangmuJingtongOpencvChuyi/img/cancelfullscreen.png
ShiyongJisuanjiShijueShizhanXiangmuJingtongOpencvChuyi/img/close.png
ShiyongJisuanjiShijueShizhanXiangmuJingtongOpencvChuyi/img/fullscreen.png
ShiyongJisuanjiShijueShizhanXiangmuJingtongOpencvChuyi/img/loader.gif
ShiyongJisuanjiShijueShizhanXiangmuJingtongOpencvChuyi/img/menu-icon.png
ShiyongJisuanjiShijueShizhanXiangmuJingtongOpencvChuyi/img/save.png
ShiyongJisuanjiShijueShizhanXiangmuJingtongOpencvChuyi/img/saved.png
ShiyongJisuanjiShijueShizhanXiangmuJingtongOpencvChuyi/img/settings-s.png
shiyong_jisuanji_shijue_shizhan_xiangmu_jingtong_opencv_chuyi-2024.3.6.0.dist-info/METADATA
shiyong_jisuanji_shijue_shizhan_xiangmu_jingtong_opencv_chuyi-2024.3.6.0.dist-info/WHEEL
shiyong_jisuanji_shijue_shizhan_xiangmu_jingtong_opencv_chuyi-2024.3.6.0.dist-info/entry_points.txt
shiyong_jisuanji_shijue_shizhan_xiangmu_jingtong_opencv_chuyi-2024.3.6.0.dist-info/top_level.txt
shiyong_jisuanji_shijue_shizhan_xiangmu_jingtong_opencv_chuyi-2024.3.6.0.dist-info/RECORD
